kfp_tekton/__init__.py
kfp_tekton/_client.py
kfp_tekton/k8s_client_helper.py
kfp_tekton/tekton.py
kfp_tekton/compiler/__init__.py
kfp_tekton/compiler/_data_passing_rewriter.py
kfp_tekton/compiler/_k8s_helper.py
kfp_tekton/compiler/_op_to_template.py
kfp_tekton/compiler/_tekton_handler.py
kfp_tekton/compiler/compiler.py
kfp_tekton/compiler/main.py
kfp_tekton/compiler/pipeline_utils.py
kfp_tekton/compiler/yaml_utils.py
kfp_tekton-1.1.0.dist-info/METADATA
kfp_tekton-1.1.0.dist-info/WHEEL
kfp_tekton-1.1.0.dist-info/entry_points.txt
kfp_tekton-1.1.0.dist-info/top_level.txt
kfp_tekton-1.1.0.dist-info/RECORD
